LICENSE
setup.py
resources/testdata/TestDefinition/README
resources/testdata/TestDefinition/render.pomset
resources/testdata/TestExecute/count1
resources/testdata/TestExecute/count2
resources/testdata/TestExecute/text1
resources/testdata/TestExecute/text2
resources/testdata/TestExecute/wordcount.py
resources/testdata/TestExecute/wordcount_reduce.py
resources/testdata/TestExecuteEucalyptus/config
resources/testdata/TestExecuteRemote/config
resources/testdata/TestHadoop/config
resources/testdata/TestHadoop/wordcount/mapper.py
resources/testdata/TestHadoop/wordcount/reducer.py
resources/testdata/TestLibrary/foo.pomset
resources/testdata/TestLibrary/library/load list values from files_fc6175d6-c18b-4403-9b79-bd2b0b0012ff.pomset
resources/testdata/TestLibrary/library/loadLibraryDefinition.pomset
resources/testdata/TestLibrary/library/loadLibraryDefinitions.pomset
resources/testdata/TestLibrary/library/word count reducer_08979d5f-6c0d-43b7-9206-dfe69eae6c26.pomset
resources/testdata/TestLibrary/library/word count_8613fe86-e7fc-4487-b4d2-0989706f8825.pomset
resources/testdata/TestLibrary/libraryFailure1/loadLibraryDefinition.pomset
resources/testdata/TestLibrary/libraryFailure1/loadLibraryDefinitions.pomset
resources/testdata/TestLibrary/libraryFailure2/loadLibraryDefinition.pomset
resources/testdata/TestLibrary/libraryFailure2/loadLibraryDefinitions.pomset
resources/testdata/TestLibrary/libraryFailure2/word count reducer_08979d5f-6c0d-43b7-9206-dfe69eae6c26.pomset
resources/testdata/TestOperator/listValues1
src/pomsets/__init__.py
src/pomsets/automaton.py
src/pomsets/builder.py
src/pomsets/command.py
src/pomsets/context.py
src/pomsets/definition.py
src/pomsets/error.py
src/pomsets/file.py
src/pomsets/hadoop.py
src/pomsets/library.py
src/pomsets/parameter.py
src/pomsets/resource.py
src/pomsets/task.py
src/pomsets/test_utils.py
src/pomsets/writer.py
src/pomsets/graph/__init__.py
src/pomsets/picloud/__init__.py
src/pomsets/python/__init__.py
src/pomsets/python/operator.py
src/pomsets_core.egg-info/PKG-INFO
src/pomsets_core.egg-info/SOURCES.txt
src/pomsets_core.egg-info/dependency_links.txt
src/pomsets_core.egg-info/requires.txt
src/pomsets_core.egg-info/top_level.txt
