Metadata-Version: 1.0
Name: pomsets-core
Version: 1.0.9
Summary: workflow management for the cloud
Home-page: http://pomsets.org
Author: michael j pan
Author-email: mjpan@pomsets.org
License: GPL (personal use) or commercial
Keywords: workflow cloud hadoop parameter sweep
Platform: All
